{
    "credit": "Made by OfficialMajonaise using Blockbench. For more models see sketchfab.com/officialmajonaise",
    "textures": {
        "0": "pubgmc:items/smoke"
    },
    "elements": [
        {
            "name": "hexadecagon",
            "from": [7.60218, 0, 6],
            "to": [8.39782, 8, 10],
            "rotation": {"angle": -45, "axis": "y", "origin": [8, 8.5, 8]},
            "faces": {
                "north": {"uv": [12, 7, 13, 13], "texture": "#0"},
                "east": {"uv": [0, 0, 1, 1], "texture": "#0"},
                "south": {"uv": [12, 7, 13, 13], "texture": "#0"},
                "west": {"uv": [0, 0, 1, 1], "texture": "#0"},
                "up": {"uv": [12, 1, 15.5, 3], "texture": "#0"},
                "down": {"uv": [0, 0, 1, 1], "texture": "#0"}
            }
        },
        {
            "name": "hexadecagon",
            "from": [7.60218, 8, 9.8],
            "to": [8.39782, 8.4, 10],
            "rotation": {"angle": -45, "axis": "y", "origin": [8, 16.5, 8]},
            "faces": {
                "north": {"uv": [13, 4.5, 14, 5.5], "texture": "#0"},
                "east": {"uv": [13, 4.5, 14, 5.5], "texture": "#0"},
                "south": {"uv": [13, 4.5, 14, 5.5], "texture": "#0"},
                "west": {"uv": [13, 4.5, 14, 5.5], "texture": "#0"},
                "up": {"uv": [13, 4.5, 14, 5.5], "texture": "#0"},
                "down": {"uv": [13, 4.5, 14, 5.5], "texture": "#0"}
            }
        },
        {
            "name": "hexadecagon",
            "from": [7.60218, 8, 6],
            "to": [8.39782, 8.4, 6.2],
            "rotation": {"angle": -45, "axis": "y", "origin": [8, 16.5, 8]},
            "faces": {
                "north": {"uv": [13, 4.5, 14, 5.5], "texture": "#0"},
                "east": {"uv": [13, 4.5, 14, 5.5], "texture": "#0"},
                "south": {"uv": [13, 4.5, 14, 5.5], "texture": "#0"},
                "west": {"uv": [13, 4.5, 14, 5.5], "texture": "#0"},
                "up": {"uv": [13, 4.5, 14, 5.5], "texture": "#0"},
                "down": {"uv": [13, 4.5, 14, 5.5], "texture": "#0"}
            }
        },
        {
            "name": "hexadecagon",
            "from": [7.60218, 0, 6],
            "to": [8.39782, 8, 10],
            "rotation": {"angle": -22.5, "axis": "y", "origin": [8, 8.5, 8]},
            "faces": {
                "north": {"uv": [12, 7, 13, 13], "texture": "#0"},
                "east": {"uv": [0, 0, 1, 1], "texture": "#0"},
                "south": {"uv": [12, 7, 13, 13], "texture": "#0"},
                "west": {"uv": [0, 0, 1, 1], "texture": "#0"},
                "up": {"uv": [12, 1, 15.5, 3], "texture": "#0"},
                "down": {"uv": [0, 0, 1, 1], "texture": "#0"}
            }
        },
        {
            "name": "hexadecagon",
            "from": [7.60218, 8, 9.8],
            "to": [8.39782, 8.4, 10],
            "rotation": {"angle": -22.5, "axis": "y", "origin": [8, 16.5, 8]},
            "faces": {
                "north": {"uv": [13, 4.5, 14, 5.5], "texture": "#0"},
                "east": {"uv": [13, 4.5, 14, 5.5], "texture": "#0"},
                "south": {"uv": [13, 4.5, 14, 5.5], "texture": "#0"},
                "west": {"uv": [13, 4.5, 14, 5.5], "texture": "#0"},
                "up": {"uv": [13, 4.5, 14, 5.5], "texture": "#0"},
                "down": {"uv": [13, 4.5, 14, 5.5], "texture": "#0"}
            }
        },
        {
            "name": "hexadecagon",
            "from": [7.60218, 8, 6],
            "to": [8.39782, 8.4, 6.2],
            "rotation": {"angle": -22.5, "axis": "y", "origin": [8, 16.5, 8]},
            "faces": {
                "north": {"uv": [13, 4.5, 14, 5.5], "texture": "#0"},
                "east": {"uv": [13, 4.5, 14, 5.5], "texture": "#0"},
                "south": {"uv": [13, 4.5, 14, 5.5], "texture": "#0"},
                "west": {"uv": [13, 4.5, 14, 5.5], "texture": "#0"},
                "up": {"uv": [13, 4.5, 14, 5.5], "texture": "#0"},
                "down": {"uv": [13, 4.5, 14, 5.5], "texture": "#0"}
            }
        },
        {
            "name": "hexadecagon",
            "from": [7.60218, 0, 6],
            "to": [8.39782, 8, 10],
            "rotation": {"angle": 0, "axis": "y", "origin": [8, 8.5, 8]},
            "faces": {
                "north": {"uv": [12, 7, 13, 13], "texture": "#0"},
                "east": {"uv": [0, 0, 1, 1], "texture": "#0"},
                "south": {"uv": [12, 7, 13, 13], "texture": "#0"},
                "west": {"uv": [0, 0, 1, 1], "texture": "#0"},
                "up": {"uv": [12, 1, 15.5, 3], "texture": "#0"},
                "down": {"uv": [0, 0, 1, 1], "texture": "#0"}
            }
        },
        {
            "name": "hexadecagon",
            "from": [7.60218, 8, 9.8],
            "to": [8.39782, 8.4, 10],
            "rotation": {"angle": 0, "axis": "y", "origin": [8, 16.5, 8]},
            "faces": {
                "north": {"uv": [13, 4.5, 14, 5.5], "texture": "#0"},
                "east": {"uv": [13, 4.5, 14, 5.5], "texture": "#0"},
                "south": {"uv": [13, 4.5, 14, 5.5], "texture": "#0"},
                "west": {"uv": [13, 4.5, 14, 5.5], "texture": "#0"},
                "up": {"uv": [13, 4.5, 14, 5.5], "texture": "#0"},
                "down": {"uv": [13, 4.5, 14, 5.5], "texture": "#0"}
            }
        },
        {
            "name": "hexadecagon",
            "from": [7.60218, 8, 6],
            "to": [8.39782, 8.4, 6.2],
            "rotation": {"angle": 0, "axis": "y", "origin": [8, 16.5, 8]},
            "faces": {
                "north": {"uv": [13, 4.5, 14, 5.5], "texture": "#0"},
                "east": {"uv": [13, 4.5, 14, 5.5], "texture": "#0"},
                "south": {"uv": [13, 4.5, 14, 5.5], "texture": "#0"},
                "west": {"uv": [13, 4.5, 14, 5.5], "texture": "#0"},
                "up": {"uv": [13, 4.5, 14, 5.5], "texture": "#0"},
                "down": {"uv": [13, 4.5, 14, 5.5], "texture": "#0"}
            }
        },
        {
            "name": "hexadecagon",
            "from": [7.60218, 0, 6],
            "to": [8.39782, 8, 10],
            "rotation": {"angle": 22.5, "axis": "y", "origin": [8, 8.5, 8]},
            "faces": {
                "north": {"uv": [12, 7, 13, 13], "texture": "#0"},
                "east": {"uv": [0, 0, 1, 1], "texture": "#0"},
                "south": {"uv": [12, 7, 13, 13], "texture": "#0"},
                "west": {"uv": [0, 0, 1, 1], "texture": "#0"},
                "up": {"uv": [12, 1, 15.5, 3], "texture": "#0"},
                "down": {"uv": [0, 0, 1, 1], "texture": "#0"}
            }
        },
        {
            "name": "hexadecagon",
            "from": [7.60218, 8, 9.8],
            "to": [8.39782, 8.4, 10],
            "rotation": {"angle": 22.5, "axis": "y", "origin": [8, 16.5, 8]},
            "faces": {
                "north": {"uv": [13, 4.5, 14, 5.5], "texture": "#0"},
                "east": {"uv": [13, 4.5, 14, 5.5], "texture": "#0"},
                "south": {"uv": [13, 4.5, 14, 5.5], "texture": "#0"},
                "west": {"uv": [13, 4.5, 14, 5.5], "texture": "#0"},
                "up": {"uv": [13, 4.5, 14, 5.5], "texture": "#0"},
                "down": {"uv": [13, 4.5, 14, 5.5], "texture": "#0"}
            }
        },
        {
            "name": "hexadecagon",
            "from": [7.60218, 8, 6],
            "to": [8.39782, 8.4, 6.2],
            "rotation": {"angle": 22.5, "axis": "y", "origin": [8, 16.5, 8]},
            "faces": {
                "north": {"uv": [13, 4.5, 14, 5.5], "texture": "#0"},
                "east": {"uv": [13, 4.5, 14, 5.5], "texture": "#0"},
                "south": {"uv": [13, 4.5, 14, 5.5], "texture": "#0"},
                "west": {"uv": [13, 4.5, 14, 5.5], "texture": "#0"},
                "up": {"uv": [13, 4.5, 14, 5.5], "texture": "#0"},
                "down": {"uv": [13, 4.5, 14, 5.5], "texture": "#0"}
            }
        },
        {
            "name": "hexadecagon",
            "from": [7.60218, 0, 6],
            "to": [8.39782, 8, 10],
            "rotation": {"angle": 45, "axis": "y", "origin": [8, 8.5, 8]},
            "faces": {
                "north": {"uv": [12, 7, 13, 13], "texture": "#0"},
                "east": {"uv": [0, 0, 1, 1], "texture": "#0"},
                "south": {"uv": [12, 7, 13, 13], "texture": "#0"},
                "west": {"uv": [0, 0, 1, 1], "texture": "#0"},
                "up": {"uv": [12, 1, 15.5, 3], "texture": "#0"},
                "down": {"uv": [0, 0, 1, 1], "texture": "#0"}
            }
        },
        {
            "name": "hexadecagon",
            "from": [7.60218, 8, 9.8],
            "to": [8.39782, 8.4, 10],
            "rotation": {"angle": 45, "axis": "y", "origin": [8, 16.5, 8]},
            "faces": {
                "north": {"uv": [13, 4.5, 14, 5.5], "texture": "#0"},
                "east": {"uv": [13, 4.5, 14, 5.5], "texture": "#0"},
                "south": {"uv": [13, 4.5, 14, 5.5], "texture": "#0"},
                "west": {"uv": [13, 4.5, 14, 5.5], "texture": "#0"},
                "up": {"uv": [13, 4.5, 14, 5.5], "texture": "#0"},
                "down": {"uv": [13, 4.5, 14, 5.5], "texture": "#0"}
            }
        },
        {
            "name": "hexadecagon",
            "from": [7.60218, 8, 6],
            "to": [8.39782, 8.4, 6.2],
            "rotation": {"angle": 45, "axis": "y", "origin": [8, 16.5, 8]},
            "faces": {
                "north": {"uv": [13, 4.5, 14, 5.5], "texture": "#0"},
                "east": {"uv": [13, 4.5, 14, 5.5], "texture": "#0"},
                "south": {"uv": [13, 4.5, 14, 5.5], "texture": "#0"},
                "west": {"uv": [13, 4.5, 14, 5.5], "texture": "#0"},
                "up": {"uv": [13, 4.5, 14, 5.5], "texture": "#0"},
                "down": {"uv": [13, 4.5, 14, 5.5], "texture": "#0"}
            }
        },
        {
            "name": "hexadecagon",
            "from": [6, 0, 7.60218],
            "to": [10, 8, 8.39782],
            "rotation": {"angle": -22.5, "axis": "y", "origin": [8, 8.5, 8]},
            "faces": {
                "north": {"uv": [0, 0, 1, 1], "texture": "#0"},
                "east": {"uv": [12, 7, 13, 13], "texture": "#0"},
                "south": {"uv": [0, 0, 1, 1], "texture": "#0"},
                "west": {"uv": [12, 7, 13, 13], "texture": "#0"},
                "up": {"uv": [12, 1, 15.5, 3], "texture": "#0"},
                "down": {"uv": [0, 0, 1, 1], "texture": "#0"}
            }
        },
        {
            "name": "hexadecagon",
            "from": [9.8, 8, 7.60218],
            "to": [10, 8.4, 8.39782],
            "rotation": {"angle": -22.5, "axis": "y", "origin": [8, 16.5, 8]},
            "faces": {
                "north": {"uv": [13, 4.5, 14, 5.5], "texture": "#0"},
                "east": {"uv": [13, 4.5, 14, 5.5], "texture": "#0"},
                "south": {"uv": [13, 4.5, 14, 5.5], "texture": "#0"},
                "west": {"uv": [13, 4.5, 14, 5.5], "texture": "#0"},
                "up": {"uv": [13, 4.5, 14, 5.5], "texture": "#0"},
                "down": {"uv": [13, 4.5, 14, 5.5], "texture": "#0"}
            }
        },
        {
            "name": "hexadecagon",
            "from": [6, 8, 7.60218],
            "to": [6.2, 8.4, 8.39782],
            "rotation": {"angle": -22.5, "axis": "y", "origin": [8, 16.5, 8]},
            "faces": {
                "north": {"uv": [13, 4.5, 14, 5.5], "texture": "#0"},
                "east": {"uv": [13, 4.5, 14, 5.5], "texture": "#0"},
                "south": {"uv": [13, 4.5, 14, 5.5], "texture": "#0"},
                "west": {"uv": [13, 4.5, 14, 5.5], "texture": "#0"},
                "up": {"uv": [13, 4.5, 14, 5.5], "texture": "#0"},
                "down": {"uv": [13, 4.5, 14, 5.5], "texture": "#0"}
            }
        },
        {
            "name": "hexadecagon",
            "from": [6, 0, 7.60218],
            "to": [10, 8, 8.39782],
            "rotation": {"angle": 0, "axis": "y", "origin": [8, 8.5, 8]},
            "faces": {
                "north": {"uv": [0, 0, 1, 1], "texture": "#0"},
                "east": {"uv": [12, 7, 13, 13], "texture": "#0"},
                "south": {"uv": [0, 0, 1, 1], "texture": "#0"},
                "west": {"uv": [12, 7, 13, 13], "texture": "#0"},
                "up": {"uv": [12, 1, 15.5, 3], "texture": "#0"},
                "down": {"uv": [0, 0, 1, 1], "texture": "#0"}
            }
        },
        {
            "name": "hexadecagon",
            "from": [9.8, 8, 7.60218],
            "to": [10, 8.4, 8.39782],
            "rotation": {"angle": 0, "axis": "y", "origin": [8, 16.5, 8]},
            "faces": {
                "north": {"uv": [13, 4.5, 14, 5.5], "texture": "#0"},
                "east": {"uv": [13, 4.5, 14, 5.5], "texture": "#0"},
                "south": {"uv": [13, 4.5, 14, 5.5], "texture": "#0"},
                "west": {"uv": [13, 4.5, 14, 5.5], "texture": "#0"},
                "up": {"uv": [13, 4.5, 14, 5.5], "texture": "#0"},
                "down": {"uv": [13, 4.5, 14, 5.5], "texture": "#0"}
            }
        },
        {
            "name": "hexadecagon",
            "from": [6, 8, 7.60218],
            "to": [6.2, 8.4, 8.39782],
            "rotation": {"angle": 0, "axis": "y", "origin": [8, 16.5, 8]},
            "faces": {
                "north": {"uv": [13, 4.5, 14, 5.5], "texture": "#0"},
                "east": {"uv": [13, 4.5, 14, 5.5], "texture": "#0"},
                "south": {"uv": [13, 4.5, 14, 5.5], "texture": "#0"},
                "west": {"uv": [13, 4.5, 14, 5.5], "texture": "#0"},
                "up": {"uv": [13, 4.5, 14, 5.5], "texture": "#0"},
                "down": {"uv": [13, 4.5, 14, 5.5], "texture": "#0"}
            }
        },
        {
            "name": "hexadecagon",
            "from": [6, 0, 7.60218],
            "to": [10, 8, 8.39782],
            "rotation": {"angle": 22.5, "axis": "y", "origin": [8, 8.5, 8]},
            "faces": {
                "north": {"uv": [0, 0, 1, 1], "texture": "#0"},
                "east": {"uv": [12, 7, 13, 13], "texture": "#0"},
                "south": {"uv": [0, 0, 1, 1], "texture": "#0"},
                "west": {"uv": [12, 7, 13, 13], "texture": "#0"},
                "up": {"uv": [12, 1, 15.5, 3], "texture": "#0"},
                "down": {"uv": [0, 0, 1, 1], "texture": "#0"}
            }
        },
        {
            "name": "hexadecagon",
            "from": [9.8, 8, 7.60218],
            "to": [10, 8.4, 8.39782],
            "rotation": {"angle": 22.5, "axis": "y", "origin": [8, 16.5, 8]},
            "faces": {
                "north": {"uv": [13, 4.5, 14, 5.5], "texture": "#0"},
                "east": {"uv": [13, 4.5, 14, 5.5], "texture": "#0"},
                "south": {"uv": [13, 4.5, 14, 5.5], "texture": "#0"},
                "west": {"uv": [13, 4.5, 14, 5.5], "texture": "#0"},
                "up": {"uv": [13, 4.5, 14, 5.5], "texture": "#0"},
                "down": {"uv": [13, 4.5, 14, 5.5], "texture": "#0"}
            }
        },
        {
            "name": "hexadecagon",
            "from": [6, 8, 7.60218],
            "to": [6.2, 8.4, 8.39782],
            "rotation": {"angle": 22.5, "axis": "y", "origin": [8, 16.5, 8]},
            "faces": {
                "north": {"uv": [13, 4.5, 14, 5.5], "texture": "#0"},
                "east": {"uv": [13, 4.5, 14, 5.5], "texture": "#0"},
                "south": {"uv": [13, 4.5, 14, 5.5], "texture": "#0"},
                "west": {"uv": [13, 4.5, 14, 5.5], "texture": "#0"},
                "up": {"uv": [13, 4.5, 14, 5.5], "texture": "#0"},
                "down": {"uv": [13, 4.5, 14, 5.5], "texture": "#0"}
            }
        },
        {
            "from": [7, 7.228, 7],
            "to": [9, 8.228, 9],
            "rotation": {"angle": 0, "axis": "y", "origin": [16, 15.228, 16]},
            "faces": {
                "north": {"uv": [13.5, 1, 15, 2], "texture": "#0"},
                "east": {"uv": [13.5, 1, 15, 2], "texture": "#0"},
                "south": {"uv": [13.5, 1, 15, 2], "texture": "#0"},
                "west": {"uv": [13.5, 1, 15, 2], "texture": "#0"},
                "up": {"uv": [13, 5, 14.5, 6], "texture": "#0"},
                "down": {"uv": [13.5, 1, 15, 2], "texture": "#0"}
            }
        },
        {
            "from": [8.708, 7.788, 7.312],
            "to": [9.372, 8.788, 8.2],
            "rotation": {"angle": 0, "axis": "y", "origin": [15.872, 15.788, 16.112]},
            "faces": {
                "north": {"uv": [13.5, 1, 15, 2], "texture": "#0"},
                "east": {"uv": [13.5, 1, 15, 2], "texture": "#0"},
                "south": {"uv": [13.5, 1, 15, 2], "texture": "#0"},
                "west": {"uv": [13.5, 1, 15, 2], "texture": "#0"},
                "up": {"uv": [12, 1, 13.5, 2], "texture": "#0"},
                "down": {"uv": [13.5, 1, 15, 2], "texture": "#0"}
            }
        },
        {
            "from": [8.508, 9.188, 7.412],
            "to": [9.472, 9.388, 8.1],
            "rotation": {"angle": 0, "axis": "y", "origin": [15.872, 17.188, 16.112]},
            "faces": {
                "north": {"uv": [13.5, 1, 15, 2], "texture": "#0"},
                "east": {"uv": [13.5, 1, 15, 2], "texture": "#0"},
                "south": {"uv": [13.5, 1, 15, 2], "texture": "#0"},
                "west": {"uv": [13.5, 1, 15, 2], "texture": "#0"},
                "up": {"uv": [12, 1, 13.5, 2], "texture": "#0"},
                "down": {"uv": [13.5, 1, 15, 2], "texture": "#0"}
            }
        },
        {
            "from": [9.872, 9.06, 7.288],
            "to": [9.972, 9.16, 8.088],
            "rotation": {"angle": 0, "axis": "y", "origin": [16.372, 17.06, 16.1]},
            "faces": {
                "north": {"uv": [12, 5, 13.5, 6], "texture": "#0"},
                "east": {"uv": [12, 5, 13.5, 6], "texture": "#0"},
                "south": {"uv": [12, 5, 13.5, 6], "texture": "#0"},
                "west": {"uv": [12, 5, 13.5, 6], "texture": "#0"},
                "up": {"uv": [12, 5, 13.5, 6], "texture": "#0"},
                "down": {"uv": [12, 5, 13.5, 6], "texture": "#0"}
            }
        },
        {
            "from": [9.772, 9.044, 7.188],
            "to": [10.072, 9.176, 7.288],
            "rotation": {"angle": 0, "axis": "y", "origin": [16.372, 17.06, 16.1]},
            "faces": {
                "north": {"uv": [12.5, 5, 14, 6], "texture": "#0"},
                "east": {"uv": [12.5, 5, 14, 6], "texture": "#0"},
                "south": {"uv": [12.5, 5, 14, 6], "texture": "#0"},
                "west": {"uv": [12.5, 5, 14, 6], "texture": "#0"},
                "up": {"uv": [12.5, 5, 14, 6], "texture": "#0"},
                "down": {"uv": [12.5, 5, 14, 6], "texture": "#0"}
            }
        },
        {
            "from": [9.772, 8.45174, 7.188],
            "to": [10.072, 8.58374, 7.288],
            "rotation": {"angle": 0, "axis": "y", "origin": [16.372, 16.46774, 16.1]},
            "faces": {
                "north": {"uv": [12.5, 5, 14, 6], "texture": "#0"},
                "east": {"uv": [12.5, 5, 14, 6], "texture": "#0"},
                "south": {"uv": [12.5, 5, 14, 6], "texture": "#0"},
                "west": {"uv": [12.5, 5, 14, 6], "texture": "#0"},
                "up": {"uv": [12.5, 5, 14, 6], "texture": "#0"},
                "down": {"uv": [12.5, 5, 14, 6], "texture": "#0"}
            }
        },
        {
            "from": [10.15213, 8.66387, 7.188],
            "to": [10.28413, 8.96387, 7.288],
            "rotation": {"angle": 0, "axis": "z", "origin": [10.21813, 8.81387, 7.238]},
            "faces": {
                "north": {"uv": [12.5, 5, 14, 6], "rotation": 90, "texture": "#0"},
                "east": {"uv": [12.5, 5, 14, 6], "rotation": 270, "texture": "#0"},
                "south": {"uv": [12.5, 5, 14, 6], "rotation": 270, "texture": "#0"},
                "west": {"uv": [12.5, 5, 14, 6], "rotation": 270, "texture": "#0"},
                "up": {"uv": [12.5, 5, 14, 6], "rotation": 270, "texture": "#0"},
                "down": {"uv": [12.5, 5, 14, 6], "rotation": 270, "texture": "#0"}
            }
        },
        {
            "from": [9.55987, 8.66387, 7.188],
            "to": [9.69187, 8.96387, 7.288],
            "rotation": {"angle": 0, "axis": "z", "origin": [9.62587, 8.81387, 7.238]},
            "faces": {
                "north": {"uv": [12.5, 5, 14, 6], "rotation": 90, "texture": "#0"},
                "east": {"uv": [12.5, 5, 14, 6], "rotation": 270, "texture": "#0"},
                "south": {"uv": [12.5, 5, 14, 6], "rotation": 270, "texture": "#0"},
                "west": {"uv": [12.5, 5, 14, 6], "rotation": 270, "texture": "#0"},
                "up": {"uv": [12.5, 5, 14, 6], "rotation": 270, "texture": "#0"},
                "down": {"uv": [12.5, 5, 14, 6], "rotation": 270, "texture": "#0"}
            }
        },
        {
            "from": [10.0654, 8.87326, 7.188],
            "to": [10.1974, 9.17326, 7.288],
            "rotation": {"angle": 45, "axis": "z", "origin": [10.1314, 9.02326, 7.238]},
            "faces": {
                "north": {"uv": [12.5, 5, 14, 6], "rotation": 270, "texture": "#0"},
                "east": {"uv": [12.5, 5, 14, 6], "rotation": 90, "texture": "#0"},
                "south": {"uv": [12.5, 5, 14, 6], "rotation": 90, "texture": "#0"},
                "west": {"uv": [12.5, 5, 14, 6], "rotation": 90, "texture": "#0"},
                "up": {"uv": [12.5, 5, 14, 6], "rotation": 90, "texture": "#0"},
                "down": {"uv": [12.5, 5, 14, 6], "rotation": 90, "texture": "#0"}
            }
        },
        {
            "from": [9.6466, 8.45447, 7.188],
            "to": [9.7786, 8.75447, 7.288],
            "rotation": {"angle": 45, "axis": "z", "origin": [9.7126, 8.60447, 7.238]},
            "faces": {
                "north": {"uv": [12.5, 5, 14, 6], "rotation": 270, "texture": "#0"},
                "east": {"uv": [12.5, 5, 14, 6], "rotation": 90, "texture": "#0"},
                "south": {"uv": [12.5, 5, 14, 6], "rotation": 90, "texture": "#0"},
                "west": {"uv": [12.5, 5, 14, 6], "rotation": 90, "texture": "#0"},
                "up": {"uv": [12.5, 5, 14, 6], "rotation": 90, "texture": "#0"},
                "down": {"uv": [12.5, 5, 14, 6], "rotation": 90, "texture": "#0"}
            }
        },
        {
            "from": [9.5626, 8.95726, 7.188],
            "to": [9.8626, 9.08926, 7.288],
            "rotation": {"angle": 45, "axis": "z", "origin": [9.7126, 9.02326, 7.238]},
            "faces": {
                "north": {"uv": [12.5, 5, 14, 6], "texture": "#0"},
                "east": {"uv": [12.5, 5, 14, 6], "texture": "#0"},
                "south": {"uv": [12.5, 5, 14, 6], "texture": "#0"},
                "west": {"uv": [12.5, 5, 14, 6], "texture": "#0"},
                "up": {"uv": [12.5, 5, 14, 6], "texture": "#0"},
                "down": {"uv": [12.5, 5, 14, 6], "texture": "#0"}
            }
        },
        {
            "from": [9.9814, 8.53847, 7.188],
            "to": [10.2814, 8.67047, 7.288],
            "rotation": {"angle": 45, "axis": "z", "origin": [10.1314, 8.60447, 7.238]},
            "faces": {
                "north": {"uv": [12.5, 5, 14, 6], "texture": "#0"},
                "east": {"uv": [12.5, 5, 14, 6], "texture": "#0"},
                "south": {"uv": [12.5, 5, 14, 6], "texture": "#0"},
                "west": {"uv": [12.5, 5, 14, 6], "texture": "#0"},
                "up": {"uv": [12.5, 5, 14, 6], "texture": "#0"},
                "down": {"uv": [12.5, 5, 14, 6], "texture": "#0"}
            }
        },
        {
            "from": [9.39704, 9.01116, 7.412],
            "to": [10.12104, 9.21116, 8.1],
            "rotation": {"angle": -22.5, "axis": "z", "origin": [9.87904, 9.11116, 7.756]},
            "faces": {
                "north": {"uv": [13.5, 1, 15, 2], "texture": "#0"},
                "east": {"uv": [13.5, 1, 15, 2], "texture": "#0"},
                "south": {"uv": [13.5, 1, 15, 2], "texture": "#0"},
                "west": {"uv": [13.5, 1, 15, 2], "texture": "#0"},
                "up": {"uv": [12, 1, 13.5, 2], "texture": "#0"},
                "down": {"uv": [13.5, 1, 15, 2], "texture": "#0"}
            }
        },
        {
            "from": [8.00296, 9.01116, 7.412],
            "to": [8.58296, 9.21116, 8.1],
            "rotation": {"angle": 22.5, "axis": "z", "origin": [8.10096, 9.11116, 7.756]},
            "faces": {
                "north": {"uv": [13.5, 1, 15, 2], "texture": "#0"},
                "east": {"uv": [13.5, 1, 15, 2], "texture": "#0"},
                "south": {"uv": [13.5, 1, 15, 2], "texture": "#0"},
                "west": {"uv": [13.5, 1, 15, 2], "texture": "#0"},
                "up": {"uv": [12, 1, 13.5, 2], "texture": "#0"},
                "down": {"uv": [13.5, 1, 15, 2], "texture": "#0"}
            }
        },
        {
            "from": [9.98814, 7.87339, 7.412],
            "to": [10.18814, 9.07339, 8.1],
            "rotation": {"angle": 22.5, "axis": "z", "origin": [10.07014, 8.97339, 7.756]},
            "faces": {
                "north": {"uv": [13.5, 1, 15, 2], "texture": "#0"},
                "east": {"uv": [13.5, 1, 15, 2], "texture": "#0"},
                "south": {"uv": [13.5, 1, 15, 2], "texture": "#0"},
                "west": {"uv": [13.5, 1, 15, 2], "texture": "#0"},
                "up": {"uv": [12, 1, 13.5, 2], "texture": "#0"},
                "down": {"uv": [13.5, 1, 15, 2], "texture": "#0"}
            }
        },
        {
            "from": [8.808, 8.788, 7.512],
            "to": [9.272, 9.188, 8],
            "rotation": {"angle": 0, "axis": "y", "origin": [15.872, 16.788, 16.112]},
            "faces": {
                "north": {"uv": [13.5, 1, 15, 2], "texture": "#0"},
                "east": {"uv": [13.5, 1, 15, 2], "texture": "#0"},
                "south": {"uv": [13.5, 1, 15, 2], "texture": "#0"},
                "west": {"uv": [13.5, 1, 15, 2], "texture": "#0"},
                "up": {"uv": [12, 1, 13.5, 2], "texture": "#0"},
                "down": {"uv": [13.5, 1, 15, 2], "texture": "#0"}
            }
        }
    ],
    "display": {
        "thirdperson_righthand": {
            "scale": [0.4, 0.4, 0.4],
            "translation": [0, 2.5, 0]
        },
        "thirdperson_lefthand": {
            "scale": [0.4, 0.4, 0.4],
            "translation": [0, 2.5, 0]
        },
        "firstperson_righthand": {
            "scale": [0.4, 0.4, 0.4],
            "translation": [0, 2.5, 0]
        },
        "firstperson_lefthand": {
            "scale": [0.4, 0.4, 0.4],
            "translation": [0, 2.5, 0]
        },
        "ground": {
            "scale": [0.4, 0.4, 0.4],
            "translation": [0, 0, 0],
            "rotation": [0, 0, 0]
        },
        "fixed": {
            "scale": [0.8, 0.8, 0.8],
            "translation": [0, 1.5, 0]
        },
        "gui": {
            "scale": [0.7, 0.7, 0.7],
            "translation": [0, 0.5, 0],
            "rotation": [30, 45, 0]
        }
    },
    "groups": [
        {
            "name": "hexadecagon",
            "origin": [8, 8, 8],
            "children": [0, 1, 2, 3, 4, 5, 6, 7, 8, 9, 10, 11, 12, 13, 14, 15, 16, 17, 18, 19, 20, 21, 22, 23, 24, 25, 26, 27, 28, 29, 30, 31, 32, 33, 34, 35, 36, 37, 38, 39]
        }
    ]
}